simcem/KilnData.py
simcem/__init__.py
simcem/clinker.py
simcem/core.cpp
simcem/core.cpython-311-x86_64-linux-gnu.so
simcem/distillation.py
simcem/free_database.xml
simcem/kiln.py
simcem/kiln_core.cpp
simcem/kiln_core.cpython-311-x86_64-linux-gnu.so
simcem/libhsl.so
simcem.libs/libblas-fe34f726.so.3.8.0
simcem.libs/libgfortran-83c28eba.so.5.0.0
simcem.libs/liblapack-31d7d384.so.3.8.0
simcem.libs/libquadmath-2284e583.so.0.0.0
simcem-1.0.0.dist-info/METADATA
simcem-1.0.0.dist-info/WHEEL
simcem-1.0.0.dist-info/RECORD
simcem-1.0.0.dist-info/licenses/LICENSE
simcem-1.0.0.dist-info/sboms/auditwheel.cdx.json
