Metadata-Version: 2.2
Name: simcem
Version: 1.0.0
Summary: SimCem, the thermodynamics/process engineering package
Author-Email: Marcus Bannerman <m.bannerman@gmail.com>
Classifier: Development Status :: 4 - Beta
Classifier: License :: OSI Approved :: MIT License
Classifier: Programming Language :: Python :: 3 :: Only
Classifier: Programming Language :: Python :: 3.7
Classifier: Programming Language :: Python :: 3.8
Classifier: Programming Language :: Python :: 3.9
Classifier: Programming Language :: Python :: 3.10
Classifier: Programming Language :: Python :: 3.11
Classifier: Programming Language :: Python :: 3.12
Classifier: Programming Language :: Python :: 3.13
Requires-Python: >=3.9
Requires-Dist: scipy
Requires-Dist: numpy
Provides-Extra: test
Requires-Dist: pytest; extra == "test"
